lcov_cobertura/lcov_cobertura.py
lcov_cobertura-2.0.2.dist-info/LICENSE
lcov_cobertura-2.0.2.dist-info/METADATA
lcov_cobertura-2.0.2.dist-info/WHEEL
lcov_cobertura-2.0.2.dist-info/entry_points.txt
lcov_cobertura-2.0.2.dist-info/top_level.txt
lcov_cobertura-2.0.2.dist-info/RECORD
