Metadata-Version: 2.1
Name: lcov-cobertura
Version: 2.0.2
Summary: LCOV to Cobertura XML converter
Home-page: https://eriwen.github.io/lcov-to-cobertura-xml/
Download-URL: https://raw.githubusercontent.com/eriwen/lcov-to-cobertura-xml/master/lcov_cobertura/lcov_cobertura.py
Author: Eric Wendelin
Author-email: me@eriwen.com
Maintainer: Steve Arnold
Maintainer-email: nerdboy@gentoo.org
License: Apache License, Version 2.0
Keywords: lcov,cobertura
Classifier: Programming Language :: Python
Classifier: Intended Audience :: Developers
Classifier: Natural Language :: English
Classifier: License :: OSI Approved :: Apache Software License
Classifier: Operating System :: OS Independent
Classifier: Topic :: Software Development :: Testing
Classifier: Topic :: Software Development :: Quality Assurance
Classifier: Development Status :: 5 - Production/Stable
Classifier: Programming Language :: Python :: 3
Classifier: Programming Language :: Python :: 3.6
Classifier: Programming Language :: Python :: 3.7
Classifier: Programming Language :: Python :: 3.8
Classifier: Programming Language :: Python :: 3.9
Requires-Python: >=3.6
License-File: LICENSE
Provides-Extra: all
Requires-Dist: pytest-cov ; extra == 'all'
Requires-Dist: coverage[toml] ; extra == 'all'
Requires-Dist: sphinx ; extra == 'all'
Requires-Dist: recommonmark ; extra == 'all'
Requires-Dist: sphinx-rtd-theme ; extra == 'all'
Requires-Dist: sphinxcontrib-apidoc ; extra == 'all'
Requires-Dist: pytest ; extra == 'all'
Requires-Dist: xmldiff ; extra == 'all'
Provides-Extra: cov
Requires-Dist: pytest-cov ; extra == 'cov'
Requires-Dist: coverage[toml] ; extra == 'cov'
Provides-Extra: doc
Requires-Dist: sphinx ; extra == 'doc'
Requires-Dist: recommonmark ; extra == 'doc'
Requires-Dist: sphinx-rtd-theme ; extra == 'doc'
Requires-Dist: sphinxcontrib-apidoc ; extra == 'doc'
Provides-Extra: test
Requires-Dist: pytest ; extra == 'test'
Requires-Dist: xmldiff ; extra == 'test'
